swiftwind_heroku/__init__.py
swiftwind_heroku/celery.py
swiftwind_heroku/settings.py
swiftwind_heroku/urls.py
swiftwind_heroku/wsgi.py
swiftwind_heroku/management/__init__.py
swiftwind_heroku/management/commands/__init__.py
swiftwind_heroku/management/commands/create_superuser_with_password.py
swiftwind_heroku-0.2.0.dist-info/DESCRIPTION.rst
swiftwind_heroku-0.2.0.dist-info/METADATA
swiftwind_heroku-0.2.0.dist-info/RECORD
swiftwind_heroku-0.2.0.dist-info/WHEEL
swiftwind_heroku-0.2.0.dist-info/metadata.json
swiftwind_heroku-0.2.0.dist-info/top_level.txt
