Metadata-Version: 2.0
Name: swiftwind-heroku
Version: 0.2.0
Summary: Swiftwind for Heroku Deployment
Home-page: https://github.com/adamcharnock/swiftwind-heroku
Author: Adam Charnock
Author-email: adam@adamcharnock.com
License: MIT
Platform: UNKNOWN
Requires-Dist: dj-database-url
Requires-Dist: dj-static
Requires-Dist: swiftwind
